{
"result":{
"players":[
{
"account_id":4294967295,
"player_slot":0,
"hero_id":101,
"item_0":206,
"item_1":77,
"item_2":77,
"item_3":29,
"item_4":232,
"item_5":36,
"backpack_0":0,
"backpack_1":0,
"backpack_2":0,
"item_neutral":358,
"kills":5,
"deaths":6,
"assists":5,
"leaver_status":0,
"last_hits":17,
"denies":2,
"gold_per_min":801,
"xp_per_min":691,
"level":11,
"hero_damage":9901,
"tower_damage":34,
"hero_healing":0,
"gold":1723,
"gold_spent":7925,
"scaled_hero_damage":8097,
"scaled_tower_damage":16,
"scaled_hero_healing":0,
"ability_upgrades":[
{
"ability":5581,
"time":213,
"level":1
},
{
"ability":5582,
"time":220,
"level":2
},
{
"ability":5583,
"time":292,
"level":3
},
{
"ability":5581,
"time":361,
"level":4
},
{
"ability":5581,
"time":423,
"level":5
},
{
"ability":5584,
"time":479,
"level":6
},
{
"ability":5581,
"time":544,
"level":7
},
{
"ability":5583,
"time":646,
"level":8
},
{
"ability":5583,
"time":691,
"level":9
},
{
"ability":5583,
"time":714,
"level":10
},
{
"ability":5965,
"time":753,
"level":11
}
]
,
"custom_game":{
"team":2,
"winner":false
}
},
{
"account_id":4294967295,
"player_slot":1,
"hero_id":27,
"item_0":223,
"item_1":34,
"item_2":218,
"item_3":29,
"item_4":232,
"item_5":0,
"backpack_0":41,
"backpack_1":0,
"backpack_2":0,
"item_neutral":290,
"kills":3,
"deaths":5,
"assists":7,
"leaver_status":0,
"last_hits":38,
"denies":0,
"gold_per_min":796,
"xp_per_min":722,
"level":12,
"hero_damage":3793,
"tower_damage":523,
"hero_healing":0,
"gold":1104,
"gold_spent":7640,
"scaled_hero_damage":2670,
"scaled_tower_damage":230,
"scaled_hero_healing":0,
"ability_upgrades":[
{
"ability":5078,
"time":160,
"level":1
},
{
"ability":5080,
"time":233,
"level":2
},
{
"ability":5078,
"time":308,
"level":3
},
{
"ability":5079,
"time":373,
"level":4
},
{
"ability":5078,
"time":422,
"level":5
},
{
"ability":5081,
"time":473,
"level":6
},
{
"ability":5078,
"time":543,
"level":7
},
{
"ability":5080,
"time":611,
"level":8
},
{
"ability":5079,
"time":678,
"level":9
},
{
"ability":5080,
"time":704,
"level":10
},
{
"ability":5079,
"time":724,
"level":11
},
{
"ability":5081,
"time":769,
"level":12
}
]
,
"custom_game":{
"team":2,
"winner":false
}
},
{
"account_id":4294967295,
"player_slot":2,
"hero_id":39,
"item_0":63,
"item_1":158,
"item_2":216,
"item_3":0,
"item_4":0,
"item_5":0,
"backpack_0":375,
"backpack_1":0,
"backpack_2":0,
"item_neutral":331,
"kills":1,
"deaths":3,
"assists":1,
"leaver_status":0,
"last_hits":59,
"denies":4,
"gold_per_min":735,
"xp_per_min":742,
"level":12,
"hero_damage":6043,
"tower_damage":506,
"hero_healing":0,
"gold":1610,
"gold_spent":7220,
"scaled_hero_damage":4021,
"scaled_tower_damage":463,
"scaled_hero_healing":0,
"ability_upgrades":[
{
"ability":5173,
"time":192,
"level":1
},
{
"ability":5174,
"time":236,
"level":2
},
{
"ability":5175,
"time":294,
"level":3
},
{
"ability":5173,
"time":359,
"level":4
},
{
"ability":5175,
"time":422,
"level":5
},
{
"ability":5176,
"time":474,
"level":6
},
{
"ability":5175,
"time":545,
"level":7
},
{
"ability":5175,
"time":587,
"level":8
},
{
"ability":5174,
"time":701,
"level":9
},
{
"ability":5173,
"time":727,
"level":10
},
{
"ability":5960,
"time":736,
"level":11
}
]
,
"custom_game":{
"team":2,
"winner":false
}
},
{
"account_id":4294967295,
"player_slot":3,
"hero_id":74,
"item_0":48,
"item_1":16,
"item_2":16,
"item_3":98,
"item_4":0,
"item_5":77,
"backpack_0":0,
"backpack_1":0,
"backpack_2":0,
"item_neutral":0,
"kills":2,
"deaths":1,
"assists":5,
"leaver_status":0,
"last_hits":16,
"denies":1,
"gold_per_min":692,
"xp_per_min":685,
"level":11,
"hero_damage":3470,
"tower_damage":0,
"hero_healing":0,
"gold":1567,
"gold_spent":6760,
"scaled_hero_damage":2510,
"scaled_tower_damage":0,
"scaled_hero_healing":0,
"ability_upgrades":[
{
"ability":5370,
"time":176,
"level":1
},
{
"ability":5372,
"time":221,
"level":2
},
{
"ability":5372,
"time":296,
"level":3
},
{
"ability":5371,
"time":356,
"level":4
},
{
"ability":5372,
"time":423,
"level":5
},
{
"ability":5370,
"time":476,
"level":6
},
{
"ability":5370,
"time":547,
"level":7
},
{
"ability":5372,
"time":639,
"level":8
},
{
"ability":5372,
"time":694,
"level":9
},
{
"ability":5371,
"time":714,
"level":10
},
{
"ability":5372,
"time":755,
"level":11
}
]
,
"custom_game":{
"team":2,
"winner":false
}
},
{
"account_id":855687753,
"player_slot":4,
"hero_id":97,
"item_0":1,
"item_1":36,
"item_2":216,
"item_3":11,
"item_4":252,
"item_5":29,
"backpack_0":0,
"backpack_1":0,
"backpack_2":0,
"item_neutral":0,
"kills":0,
"deaths":5,
"assists":4,
"leaver_status":0,
"last_hits":10,
"denies":2,
"gold_per_min":569,
"xp_per_min":662,
"level":11,
"hero_damage":2873,
"tower_damage":0,
"hero_healing":0,
"gold":1231,
"gold_spent":5830,
"scaled_hero_damage":2067,
"scaled_tower_damage":0,
"scaled_hero_healing":0,
"ability_upgrades":[
{
"ability":5519,
"time":290,
"level":1
},
{
"ability":5518,
"time":330,
"level":2
},
{
"ability":5518,
"time":331,
"level":3
},
{
"ability":5520,
"time":393,
"level":4
},
{
"ability":5519,
"time":441,
"level":5
},
{
"ability":5521,
"time":500,
"level":6
},
{
"ability":5518,
"time":569,
"level":7
},
{
"ability":5520,
"time":686,
"level":8
},
{
"ability":5518,
"time":692,
"level":9
},
{
"ability":5519,
"time":720,
"level":10
},
{
"ability":5519,
"time":758,
"level":11
}
]
,
"custom_game":{
"team":2,
"winner":false
}
},
{
"account_id":4294967295,
"player_slot":128,
"hero_id":54,
"item_0":151,
"item_1":168,
"item_2":50,
"item_3":170,
"item_4":218,
"item_5":0,
"backpack_0":0,
"backpack_1":0,
"backpack_2":0,
"item_neutral":355,
"kills":5,
"deaths":2,
"assists":8,
"leaver_status":0,
"last_hits":45,
"denies":5,
"gold_per_min":905,
"xp_per_min":824,
"level":13,
"hero_damage":9462,
"tower_damage":229,
"hero_healing":0,
"gold":1006,
"gold_spent":9625,
"scaled_hero_damage":8249,
"scaled_tower_damage":113,
"scaled_hero_healing":0,
"ability_upgrades":[
{
"ability":5250,
"time":223,
"level":1
},
{
"ability":631,
"time":237,
"level":2
},
{
"ability":5250,
"time":276,
"level":3
},
{
"ability":5249,
"time":341,
"level":4
},
{
"ability":631,
"time":388,
"level":5
},
{
"ability":5250,
"time":425,
"level":6
},
{
"ability":5252,
"time":475,
"level":7
},
{
"ability":631,
"time":521,
"level":8
},
{
"ability":631,
"time":562,
"level":9
},
{
"ability":5918,
"time":602,
"level":10
},
{
"ability":5250,
"time":636,
"level":11
},
{
"ability":5249,
"time":681,
"level":12
},
{
"ability":5249,
"time":757,
"level":13
}
]
,
"custom_game":{
"team":3,
"winner":true
}
},
{
"account_id":4294967295,
"player_slot":129,
"hero_id":107,
"item_0":231,
"item_1":69,
"item_2":27,
"item_3":188,
"item_4":59,
"item_5":0,
"backpack_0":0,
"backpack_1":0,
"backpack_2":0,
"item_neutral":290,
"kills":0,
"deaths":3,
"assists":12,
"leaver_status":0,
"last_hits":16,
"denies":1,
"gold_per_min":725,
"xp_per_min":766,
"level":12,
"hero_damage":2427,
"tower_damage":0,
"hero_healing":1621,
"gold":802,
"gold_spent":7925,
"scaled_hero_damage":1943,
"scaled_tower_damage":0,
"scaled_hero_healing":869,
"ability_upgrades":[
{
"ability":5608,
"time":211,
"level":1
},
{
"ability":5609,
"time":238,
"level":2
},
{
"ability":5610,
"time":284,
"level":3
},
{
"ability":5608,
"time":341,
"level":4
},
{
"ability":5608,
"time":388,
"level":5
},
{
"ability":5612,
"time":431,
"level":6
},
{
"ability":5609,
"time":510,
"level":7
},
{
"ability":5609,
"time":525,
"level":8
},
{
"ability":5610,
"time":572,
"level":9
},
{
"ability":5608,
"time":625,
"level":10
},
{
"ability":5610,
"time":655,
"level":11
},
{
"ability":5612,
"time":709,
"level":12
}
]
,
"custom_game":{
"team":3,
"winner":true
}
},
{
"account_id":4294967295,
"player_slot":130,
"hero_id":9,
"item_0":29,
"item_1":36,
"item_2":240,
"item_3":108,
"item_4":104,
"item_5":0,
"backpack_0":0,
"backpack_1":0,
"backpack_2":0,
"item_neutral":304,
"kills":8,
"deaths":2,
"assists":5,
"leaver_status":0,
"last_hits":10,
"denies":1,
"gold_per_min":799,
"xp_per_min":751,
"level":12,
"hero_damage":11841,
"tower_damage":32,
"hero_healing":0,
"gold":1213,
"gold_spent":8300,
"scaled_hero_damage":9461,
"scaled_tower_damage":5,
"scaled_hero_healing":0,
"ability_upgrades":[
{
"ability":5048,
"time":164,
"level":1
},
{
"ability":5050,
"time":238,
"level":2
},
{
"ability":5051,
"time":283,
"level":3
},
{
"ability":5051,
"time":339,
"level":4
},
{
"ability":5051,
"time":392,
"level":5
},
{
"ability":5048,
"time":433,
"level":6
},
{
"ability":5051,
"time":486,
"level":7
},
{
"ability":5048,
"time":540,
"level":8
},
{
"ability":5048,
"time":579,
"level":9
},
{
"ability":5050,
"time":623,
"level":10
},
{
"ability":5049,
"time":660,
"level":11
},
{
"ability":5050,
"time":701,
"level":12
}
]
,
"custom_game":{
"team":3,
"winner":true
}
},
{
"account_id":4294967295,
"player_slot":131,
"hero_id":53,
"item_0":240,
"item_1":42,
"item_2":247,
"item_3":216,
"item_4":223,
"item_5":8,
"backpack_0":0,
"backpack_1":0,
"backpack_2":0,
"item_neutral":212,
"kills":3,
"deaths":3,
"assists":0,
"leaver_status":0,
"last_hits":46,
"denies":3,
"gold_per_min":823,
"xp_per_min":789,
"level":12,
"hero_damage":2886,
"tower_damage":4987,
"hero_healing":0,
"gold":1518,
"gold_spent":8250,
"scaled_hero_damage":3114,
"scaled_tower_damage":1965,
"scaled_hero_healing":0,
"ability_upgrades":[
{
"ability":5246,
"time":235,
"level":1
},
{
"ability":5247,
"time":237,
"level":2
},
{
"ability":5246,
"time":281,
"level":3
},
{
"ability":5245,
"time":339,
"level":4
},
{
"ability":5247,
"time":384,
"level":5
},
{
"ability":5246,
"time":422,
"level":6
},
{
"ability":5248,
"time":474,
"level":7
},
{
"ability":5247,
"time":519,
"level":8
},
{
"ability":5247,
"time":567,
"level":9
},
{
"ability":5246,
"time":607,
"level":10
},
{
"ability":5960,
"time":658,
"level":11
},
{
"ability":5248,
"time":692,
"level":12
}
]
,
"custom_game":{
"team":3,
"winner":true
}
},
{
"account_id":430798272,
"player_slot":132,
"hero_id":52,
"item_0":121,
"item_1":29,
"item_2":77,
"item_3":100,
"item_4":36,
"item_5":9,
"backpack_0":39,
"backpack_1":0,
"backpack_2":0,
"item_neutral":356,
"kills":3,
"deaths":1,
"assists":2,
"leaver_status":0,
"last_hits":127,
"denies":16,
"gold_per_min":1086,
"xp_per_min":926,
"level":14,
"hero_damage":3190,
"tower_damage":3241,
"hero_healing":0,
"gold":1178,
"gold_spent":12180,
"scaled_hero_damage":2752,
"scaled_tower_damage":1931,
"scaled_hero_healing":0,
"ability_upgrades":[
{
"ability":5242,
"time":219,
"level":1
},
{
"ability":5241,
"time":226,
"level":2
},
{
"ability":5242,
"time":273,
"level":3
},
{
"ability":5241,
"time":317,
"level":4
},
{
"ability":5243,
"time":362,
"level":5
},
{
"ability":5244,
"time":406,
"level":6
},
{
"ability":5242,
"time":442,
"level":7
},
{
"ability":5242,
"time":524,
"level":8
},
{
"ability":5243,
"time":554,
"level":9
},
{
"ability":5243,
"time":603,
"level":10
},
{
"ability":5243,
"time":639,
"level":11
},
{
"ability":5244,
"time":657,
"level":12
},
{
"ability":5241,
"time":729,
"level":13
},
{
"ability":5241,
"time":760,
"level":14
}
]
,
"custom_game":{
"team":3,
"winner":true
}
}
]
,
"radiant_win":false,
"duration":639,
"pre_game_duration":0,
"start_time":1626635614,
"match_id":6094890831,
"match_seq_num":5102043101,
"tower_status_radiant":0,
"tower_status_dire":0,
"barracks_status_radiant":0,
"barracks_status_dire":0,
"cluster":251,
"first_blood_time":123,
"lobby_type":12,
"human_players":10,
"leagueid":0,
"positive_votes":0,
"negative_votes":0,
"game_mode":19,
"flags":1,
"engine":1,
"radiant_score":11,
"dire_score":20
}
}